rocket/__init__.py
rocket/rocket.py
linearregdiaazg-1.0.0.dist-info/LICENSE.txt
linearregdiaazg-1.0.0.dist-info/METADATA
linearregdiaazg-1.0.0.dist-info/WHEEL
linearregdiaazg-1.0.0.dist-info/top_level.txt
linearregdiaazg-1.0.0.dist-info/RECORD
