Metadata-Version: 2.1
Name: linearregdiaazg
Version: 1.0.0
Summary: An awesome package that does something
Home-page: http://pypi.python.org/pypi/rocket/
Author: diaa zellagui
Author-email: md.zellagui@esi-sba.dz
License: LICENSE.txt
License-File: LICENSE.txt
Requires-Dist: numpy
